{
  "El": {
    "El_max_subth_long_square": {
      "dependencies": null, 
      "value": -0.0716780624389648
    }, 
    "El_noise": {
      "measured": {
        "dependencies": null, 
        "list": [
          -0.0713603973388672, 
          -0.0729803314208984, 
          -0.0725921173095703
        ], 
        "mean": -0.072310948689778637
      }
    }, 
    "El_ramp": {
      "dependencies": null, 
      "value": -0.07363921356201171
    }, 
    "El_suprathreshold_blip": {
      "dependencies": null, 
      "value": -0.073078498840332
    }, 
    "El_subthreshold_blip": {
      "dependencies": null, 
      "value": -0.07314971923828119
    }
  }, 
  "spike_cut_length": {
    "no deltaV shift": {
      "slope": 0.1831811853926697, 
      "length": 39.0, 
      "intercept": 0.0068382580145210986, 
      "dependencies": null
    }
  }, 
  "threshold_adaptation": {
    "b_spike_component_of_threshold": null, 
    "b_voltage_comp_of_thr_from_fitab": null, 
    "b_voltage_comp_of_thr_from_fitabth": null, 
    "a_voltage_comp_of_thr_from_fitab": null, 
    "a_spike_component_of_threshold": null, 
    "a_voltage_comp_of_thr_from_fitabth": null
  }, 
  "th_inf": {
    "via_Vmeasure": {
      "from_zero": 0.028465536198401781, 
      "dependencies": "measured from suprathreshold blip", 
      "value": -0.044612962641930223
    }, 
    "fit_with_v_comp_of_th": {
      "from_zero": null, 
      "value": null
    }
  }, 
  "resistance": {
    "R_test_list": {
      "list": [
        184494861.29480177, 
        185231987.75597239, 
        195774445.84545669
      ], 
      "mean": 188500431.63207695
    }, 
    "R_fit_ASC_and_R": {
      "list": [
        194230071.620262, 
        192881382.16182184, 
        196494188.49568814
      ], 
      "mean": 194535214.09259066
    }, 
    "R_from_lims": {
      "value": 150000110.268593
    }
  }, 
  "asc": {
    "amp": [
      -2.183108124347443e-12, 
      -5.783188606641768e-11
    ], 
    "k": [
      3.0, 
      300.0
    ], 
    "dependencies": "Cap and res from least squares"
  }, 
  "capacitance": {
    "C_from_lims": {
      "value": 5.168866580597891e-11
    }, 
    "C_test_list": {
      "list": [
        5.6123060448057647e-11, 
        5.7440108063107556e-11, 
        5.5419537182849714e-11
      ], 
      "mean": 5.6327568564671639e-11
    }
  }, 
  "MLIN": {
    "tau_from_AC": 0.0068689066752556727, 
    "sv_for_expsymm": 0.00033356733035834799, 
    "var_of_section": 2.2253432776479054e-07
  }, 
  "sweep_properties": {
    "multi_short_square": {
      "sweep_num": null
    }, 
    "noise1": {
      "1": {
        "sweep_num": 49, 
        "El": -0.0713603973388672, 
        "spike_ind": [
          250920, 
          251175, 
          253025, 
          253453, 
          255526, 
          255805, 
          256010, 
          257425, 
          259914, 
          261450, 
          261859, 
          266484, 
          271397, 
          272471, 
          272779, 
          273175, 
          273459, 
          274358, 
          276193, 
          278042, 
          278454, 
          278735, 
          279025, 
          279379, 
          279676, 
          280174, 
          280512, 
          280793, 
          281006, 
          282463, 
          284955, 
          285484, 
          286365, 
          286821, 
          294040, 
          296385, 
          297477, 
          297779, 
          298129, 
          298433, 
          299376, 
          301159, 
          301388, 
          301833, 
          302991, 
          303453, 
          303739, 
          304055, 
          304397, 
          304695, 
          305543, 
          305818, 
          306041, 
          307404, 
          308170, 
          309936, 
          310508, 
          311455, 
          316499, 
          319023, 
          321391, 
          322470, 
          322808, 
          323153, 
          323464, 
          324387, 
          450667, 
          450851, 
          451018, 
          451147, 
          451269, 
          451409, 
          451629, 
          451789, 
          451985, 
          452188, 
          452390, 
          452595, 
          452891, 
          453064, 
          453251, 
          453414, 
          453570, 
          453713, 
          453917, 
          454057, 
          454269, 
          454419, 
          454574, 
          454717, 
          455092, 
          455419, 
          455566, 
          455725, 
          455846, 
          455972, 
          456093, 
          456273, 
          457367, 
          457621, 
          457975, 
          458179, 
          458576, 
          459206, 
          459438, 
          459773, 
          459931, 
          460245, 
          460425, 
          460638, 
          460937, 
          461259, 
          461436, 
          461678, 
          461843, 
          462568, 
          463015, 
          463416, 
          464834, 
          465712, 
          466409, 
          467898, 
          468149, 
          468424, 
          468836, 
          469018, 
          469445, 
          470103, 
          470385, 
          470559, 
          470742, 
          471038, 
          471303, 
          471476, 
          471858, 
          472132, 
          472400, 
          472580, 
          472735, 
          472941, 
          473116, 
          473301, 
          473453, 
          474223, 
          474423, 
          475591, 
          475845, 
          476040, 
          476172, 
          476302, 
          476657, 
          476839, 
          477118, 
          477311, 
          477571, 
          477899, 
          478103, 
          478310, 
          478488, 
          478648, 
          478872, 
          479021, 
          479236, 
          479404, 
          479561, 
          479712, 
          480092, 
          480331, 
          480489, 
          480661, 
          480805, 
          480934, 
          481062, 
          481230, 
          481445, 
          482357, 
          482633, 
          482993, 
          483182, 
          483556, 
          484201, 
          484450, 
          484773, 
          484942, 
          485260, 
          485455, 
          485666, 
          485958, 
          486277, 
          486458, 
          486680, 
          486859, 
          487551, 
          488034, 
          488416, 
          489851, 
          490723, 
          491359, 
          491552, 
          491866, 
          492095, 
          492337, 
          493428, 
          493821, 
          494015, 
          494443, 
          494835, 
          495109, 
          495382, 
          495549, 
          495740, 
          496041, 
          496304, 
          496487, 
          496852, 
          497126, 
          497393, 
          497579, 
          497736, 
          497952, 
          498125, 
          498305, 
          498458, 
          499186, 
          499344, 
          500589, 
          500843, 
          501033, 
          501177, 
          501308, 
          501577, 
          501764, 
          501952, 
          502176, 
          502407, 
          502635, 
          502924, 
          503125, 
          503332, 
          503499, 
          503656, 
          503877, 
          504027, 
          504238, 
          504403, 
          504550, 
          504708, 
          505103, 
          505359, 
          505516, 
          505701, 
          505833, 
          505961, 
          506094, 
          506325, 
          506669, 
          506958, 
          507303, 
          507462, 
          507680, 
          508000, 
          508205, 
          508561, 
          509189, 
          509458, 
          509776, 
          509937, 
          510258, 
          510466, 
          510684, 
          510993, 
          511288, 
          511480, 
          511712, 
          511908, 
          512551, 
          513034, 
          513446, 
          514605, 
          514868, 
          515719, 
          516345, 
          516540, 
          516860, 
          517100, 
          517354, 
          517777, 
          518041, 
          518387, 
          518865, 
          519054, 
          519400, 
          520087, 
          520375, 
          520544, 
          520738, 
          521051, 
          521309, 
          521486, 
          521863, 
          522132, 
          522397, 
          522579, 
          522743, 
          522953, 
          523130, 
          523313, 
          523468, 
          524213, 
          524401
        ]
      }, 
      "3": {
        "sweep_num": 55, 
        "El": -0.0725921173095703, 
        "spike_ind": [
          250853, 
          251109, 
          251305, 
          251710, 
          255174, 
          255490, 
          255762, 
          255950, 
          256160, 
          257417, 
          259853, 
          261337, 
          261795, 
          265837, 
          266440, 
          269057, 
          269536, 
          270146, 
          270505, 
          271385, 
          272481, 
          272750, 
          273086, 
          273395, 
          274314, 
          277965, 
          278350, 
          278637, 
          278956, 
          279297, 
          279571, 
          279815, 
          280201, 
          280489, 
          280740, 
          280929, 
          281135, 
          282393, 
          284860, 
          286350, 
          286774, 
          289929, 
          291455, 
          293487, 
          294008, 
          294483, 
          295558, 
          296111, 
          296454, 
          297470, 
          297753, 
          298135, 
          298419, 
          299333, 
          301187, 
          301404, 
          301785, 
          302247, 
          302974, 
          303396, 
          303659, 
          303975, 
          304344, 
          304604, 
          304863, 
          307401, 
          308064, 
          308659, 
          309507, 
          309900, 
          310356, 
          310727, 
          311340, 
          311770, 
          314926, 
          316446, 
          319011, 
          319502, 
          321402, 
          322459, 
          322734, 
          323064, 
          323368, 
          324323, 
          450656, 
          450834, 
          450989, 
          451124, 
          451241, 
          451375, 
          451610, 
          451762, 
          451928, 
          452126, 
          452299, 
          452550, 
          452886, 
          453045, 
          453221, 
          453390, 
          453544, 
          453688, 
          453873, 
          454002, 
          454188, 
          454348, 
          454487, 
          454641, 
          454771, 
          455078, 
          455258, 
          455424, 
          455570, 
          455723, 
          455845, 
          455969, 
          456089, 
          456285, 
          457348, 
          457621, 
          457967, 
          458152, 
          458607, 
          459461, 
          459759, 
          459919, 
          460238, 
          460430, 
          460636, 
          460892, 
          461244, 
          461411, 
          461595, 
          461775, 
          462006, 
          462532, 
          462991, 
          463343, 
          464551, 
          464826, 
          465702, 
          468426, 
          468850, 
          469024, 
          470116, 
          470369, 
          470533, 
          470705, 
          471015, 
          471272, 
          471420, 
          471597, 
          471869, 
          472124, 
          472381, 
          472538, 
          472687, 
          472887, 
          473058, 
          473226, 
          473386, 
          473572, 
          474170, 
          474337, 
          475578, 
          475825, 
          476015, 
          476156, 
          476287, 
          476522, 
          476714, 
          476890, 
          477133, 
          477322, 
          477573, 
          477897, 
          478064, 
          478263, 
          478438, 
          478602, 
          478756, 
          478942, 
          479094, 
          479291, 
          479435, 
          479599, 
          479741, 
          480092, 
          480333, 
          480479, 
          480647, 
          480794, 
          480917, 
          481045, 
          481200, 
          481395, 
          481703, 
          481937, 
          482286, 
          482450, 
          482660, 
          482981, 
          483171, 
          483608, 
          484212, 
          484440, 
          484757, 
          484914, 
          485235, 
          485421, 
          485629, 
          485914, 
          486250, 
          486417, 
          486608, 
          486785, 
          487537, 
          488014, 
          488378, 
          489853, 
          490708, 
          493417, 
          493806, 
          493993, 
          494200, 
          494439, 
          494778, 
          495073, 
          495355, 
          495521, 
          495700, 
          496027, 
          496291, 
          496449, 
          496644, 
          496903, 
          497146, 
          497396, 
          497571, 
          497723, 
          497928, 
          498094, 
          498259, 
          498419, 
          499199, 
          499360, 
          500573, 
          500821, 
          501016, 
          501158, 
          501291, 
          502899, 
          503080, 
          503280, 
          503457, 
          503623, 
          503798, 
          503963, 
          504143, 
          504328, 
          504468, 
          504633, 
          504771, 
          505092, 
          505372, 
          505523, 
          505695, 
          505831, 
          505961, 
          506087, 
          506312, 
          507358, 
          507621, 
          507977, 
          508178, 
          508557, 
          509219, 
          509449, 
          509756, 
          509913, 
          510240, 
          510424, 
          510632, 
          510892, 
          511248, 
          511421, 
          511634, 
          511809, 
          512543, 
          513004, 
          513358, 
          514847, 
          515708, 
          516312, 
          516492, 
          516831, 
          517047, 
          517298, 
          517757, 
          518022, 
          518394, 
          518828, 
          519019, 
          520113, 
          520391, 
          520560, 
          520736, 
          521040, 
          521303, 
          521465, 
          521704, 
          522037, 
          522381, 
          522560, 
          522719, 
          522933, 
          523116, 
          523297, 
          523456, 
          524191, 
          524358
        ]
      }, 
      "2": {
        "sweep_num": 51, 
        "El": -0.0729803314208984, 
        "spike_ind": [
          250935, 
          251168, 
          251393, 
          251807, 
          252990, 
          257449, 
          258137, 
          259885, 
          260440, 
          264958, 
          266462, 
          269032, 
          270521, 
          271375, 
          272473, 
          272811, 
          273162, 
          273458, 
          274351, 
          276133, 
          276342, 
          276836, 
          277266, 
          277996, 
          278424, 
          278700, 
          279034, 
          279378, 
          279668, 
          280181, 
          280509, 
          280777, 
          280977, 
          282430, 
          284885, 
          285452, 
          286414, 
          286823, 
          289970, 
          291478, 
          296386, 
          297493, 
          297847, 
          298169, 
          298463, 
          299334, 
          301158, 
          301407, 
          301807, 
          303000, 
          303437, 
          303722, 
          304024, 
          304377, 
          304682, 
          305189, 
          305514, 
          305779, 
          305985, 
          307419, 
          308133, 
          309893, 
          311444, 
          311833, 
          314987, 
          316458, 
          319059, 
          320523, 
          321370, 
          322475, 
          322770, 
          323192, 
          323517, 
          324375, 
          450673, 
          450850, 
          451016, 
          451145, 
          451262, 
          451403, 
          451634, 
          451793, 
          452009, 
          452188, 
          452362, 
          452588, 
          452889, 
          453053, 
          453246, 
          453408, 
          453560, 
          453691, 
          453888, 
          454026, 
          454211, 
          454372, 
          454525, 
          454672, 
          454808, 
          455086, 
          455231, 
          455420, 
          455562, 
          455723, 
          455849, 
          455976, 
          456098, 
          456316, 
          457365, 
          457620, 
          457976, 
          458159, 
          458575, 
          459189, 
          459435, 
          459768, 
          459922, 
          460243, 
          460430, 
          460635, 
          460889, 
          461240, 
          461408, 
          461605, 
          461780, 
          462543, 
          463031, 
          463415, 
          464861, 
          465718, 
          467892, 
          468133, 
          468417, 
          468848, 
          469031, 
          469364, 
          469594, 
          470044, 
          470365, 
          470526, 
          470697, 
          471026, 
          471291, 
          471452, 
          471656, 
          471919, 
          472155, 
          472405, 
          472572, 
          472719, 
          472929, 
          473107, 
          473274, 
          473432, 
          474215, 
          474407, 
          475584, 
          475828, 
          476032, 
          476170, 
          476301, 
          476577, 
          476758, 
          476960, 
          477180, 
          477379, 
          477602, 
          477901, 
          478092, 
          478298, 
          478457, 
          478625, 
          478799, 
          478964, 
          479134, 
          479329, 
          479477, 
          479638, 
          479769, 
          480098, 
          480346, 
          480496, 
          480669, 
          480802, 
          480928, 
          481056, 
          481245, 
          481462, 
          482359, 
          482612, 
          482981, 
          483177, 
          483545, 
          484207, 
          484448, 
          484769, 
          484929, 
          485248, 
          485443, 
          485654, 
          485927, 
          486264, 
          486448, 
          486656, 
          486828, 
          487547, 
          488015, 
          488404, 
          489847, 
          490708, 
          491337, 
          491526, 
          491847, 
          492077, 
          492338, 
          492792, 
          493052, 
          493386, 
          493928, 
          494104, 
          494410, 
          495083, 
          495371, 
          495535, 
          495711, 
          496034, 
          496296, 
          496466, 
          496883, 
          497149, 
          497404, 
          497576, 
          497737, 
          497950, 
          498135, 
          498307, 
          498454, 
          499207, 
          499383, 
          500594, 
          500846, 
          501043, 
          501180, 
          501316, 
          501619, 
          501799, 
          502020, 
          502227, 
          502491, 
          502903, 
          503094, 
          503303, 
          503463, 
          503631, 
          503831, 
          503992, 
          504185, 
          504357, 
          504513, 
          504671, 
          504820, 
          505104, 
          505356, 
          505505, 
          505681, 
          505817, 
          505948, 
          506076, 
          506277, 
          507359, 
          507619, 
          507977, 
          508184, 
          508554, 
          509188, 
          509444, 
          509760, 
          509918, 
          510234, 
          510440, 
          510655, 
          510970, 
          511280, 
          511472, 
          511702, 
          511892, 
          512538, 
          513015, 
          513405, 
          514850, 
          515709, 
          516340, 
          516524, 
          516842, 
          517082, 
          517335, 
          517790, 
          518073, 
          518399, 
          518850, 
          519039, 
          519384, 
          520078, 
          520371, 
          520542, 
          520727, 
          521048, 
          521306, 
          521477, 
          521856, 
          522135, 
          522402, 
          522580, 
          522740, 
          522951, 
          523130, 
          523306, 
          523464, 
          524202, 
          524367
        ]
      }, 
      "5": {
        "sweep_num": null, 
        "El": null, 
        "spike_ind": null
      }, 
      "4": {
        "sweep_num": null, 
        "El": null, 
        "spike_ind": null
      }
    }, 
    "ramp": {
      "sweep_num": [
        5, 
        6
      ]
    }, 
    "max_subthresh_long_square": {
      "sweep_num": [
        44
      ]
    }, 
    "suprathreshold_short_square": {
      "R_testpulsesweep_num": [
        15, 
        17, 
        18, 
        19
      ]
    }, 
    "subthreshold_short_square": {
      "sweep_num": [
        16
      ]
    }
  }, 
  "spike_cutting": {
    "NOdeltaV": {
      "slope": 0.1831811853926697, 
      "intercept": 0.0068382580145210986, 
      "cut_length": 39.0, 
      "dependencies": null
    }
  }, 
  "dt_used_for_preprocessor_calculations": 5e-05
}