{
  "El_reference": -0.07445100402832033, 
  "C": 1.5978326009951426e-10, 
  "asc_amp_array": [
    -3.7755286418085606e-11, 
    -2.793490203472682e-10
  ], 
  "init_threshold": 0.026056069191936315, 
  "threshold_reset_method": {
    "params": {
      "a_spike": 0.0012766311834702328, 
      "b_spike": 88.17157667955009
    }, 
    "name": "three_components"
  }, 
  "th_inf": 0.026056069191936315, 
  "spike_cut_length": 177, 
  "init_AScurrents": [
    0.0, 
    0.0
  ], 
  "init_voltage": 0.0, 
  "threshold_dynamics_method": {
    "params": {
      "b_voltage": 0, 
      "a_spike": 0.0012766311834702328, 
      "b_spike": 88.17157667955009, 
      "a_voltage": 0
    }, 
    "name": "spike_component"
  }, 
  "voltage_reset_method": {
    "params": {
      "a": 0.6958211998707008, 
      "b": 0.0006522349219856283
    }, 
    "name": "v_before"
  }, 
  "extrapolation_method_name": "endpoints", 
  "dt": 5e-05, 
  "voltage_dynamics_method": {
    "params": {}, 
    "name": "linear_forward_euler"
  }, 
  "El": 0.0, 
  "asc_tau_array": [
    0.1, 
    0.01
  ], 
  "R_input": 239213718.80109608, 
  "AScurrent_dynamics_method": {
    "params": {}, 
    "name": "exp"
  }, 
  "AScurrent_reset_method": {
    "params": {
      "r": [
        1.0, 
        1.0
      ]
    }, 
    "name": "sum"
  }, 
  "dt_multiplier": 10, 
  "th_adapt": null, 
  "coeffs": {
    "a": 1, 
    "C": 1, 
    "b": 1, 
    "G": 1, 
    "th_inf": 1.2045512595380536, 
    "asc_amp_array": [
      1.0, 
      1.0
    ]
  }, 
  "type": "GLIF"
}