{
  "El": {
    "El_max_subth_long_square": {
      "dependencies": null,
      "value": -0.0679220199584961
    },
    "El_noise": {
      "measured": {
        "dependencies": null,
        "list": [
          -0.0690637741088867,
          -0.0701246109008789,
          -0.06922052001953119,
          -0.0684890213012695
        ],
        "mean": -0.06922448158264158
      }
    },
    "El_ramp": {
      "dependencies": null,
      "value": -0.0697356262207031
    },
    "El_suprathreshold_blip": {
      "dependencies": null,
      "value": -0.0679828796386719
    },
    "El_subthreshold_blip": {
      "dependencies": null,
      "value": -0.0686349868774414
    }
  },
  "spike_cut_length": {
    "no deltaV shift": {
      "slope": 0.3839727870053092,
      "length": 68.0,
      "intercept": 0.008822854072073658,
      "dependencies": null
    }
  },
  "threshold_adaptation": {
    "b_spike_component_of_threshold": null,
    "b_voltage_comp_of_thr_from_fitab": null,
    "b_voltage_comp_of_thr_from_fitabth": null,
    "a_voltage_comp_of_thr_from_fitab": null,
    "a_spike_component_of_threshold": null,
    "a_voltage_comp_of_thr_from_fitabth": null
  },
  "th_inf": {
    "via_Vmeasure": {
      "from_zero": 0.02186346459212825,
      "dependencies": "measured from suprathreshold blip",
      "value": -0.046119415046543655
    },
    "fit_with_v_comp_of_th": {
      "from_zero": null,
      "value": null
    }
  },
  "resistance": {
    "R_test_list": {
      "list": [
        373963047.8762063,
        352766518.94637203,
        350178108.34893525,
        332438780.7600471
      ],
      "mean": 352336613.9828901
    },
    "R_fit_ASC_and_R": {
      "list": [
        396724474.8421817,
        351188289.4433249,
        350794344.44999903,
        353231872.02354294
      ],
      "mean": 362984745.1897621
    },
    "R_from_lims": {
      "value": 271874994.039536
    }
  },
  "asc": {
    "amp": [
      -8.158198941778173e-11,
      3.4477989178445916e-10
    ],
    "k": [
      29.999999999999996,
      300.0
    ],
    "dependencies": "Cap and res from least squares"
  },
  "capacitance": {
    "C_from_lims": {
      "value": 1.2053331805269922e-10
    },
    "C_test_list": {
      "list": [
        9.178853575489454e-11,
        9.106159206959304e-11,
        1.0330218118759003e-10,
        9.296413601464525e-11
      ],
      "mean": 9.477911125668071e-11
    }
  },
  "MLIN": {
    "tau_from_AC": 0.036152163426206266,
    "sv_for_expsymm": 0.0005749185808275237,
    "var_of_section": 6.610627491614678e-07
  },
  "sweep_properties": {
    "multi_short_square": {
      "sweep_num": null
    },
    "noise1": {
      "1": {
        "sweep_num": 43,
        "El": -0.0690637741088867,
        "spike_ind": [
          202566,
          203807,
          206552,
          215034,
          217235,
          221069,
          222982,
          224603,
          228340,
          234590,
          238088,
          241093,
          243048,
          244725,
          248730,
          254482,
          257255,
          258805,
          361061,
          361737,
          362737,
          363577,
          364577,
          366168,
          367893,
          369324,
          372640,
          373875,
          375232,
          376455,
          377794,
          378719,
          380882,
          382365,
          383248,
          384405,
          385939,
          387857,
          389406,
          393075,
          394551,
          396202,
          397272,
          398207,
          400716,
          401518,
          402782,
          403693,
          404599,
          406170,
          407892,
          409305,
          412673,
          414503,
          416369,
          417956,
          418810
        ]
      },
      "3": {
        "sweep_num": 47,
        "El": -0.06922052001953119,
        "spike_ind": [
          203180,
          204850,
          217136,
          222590,
          224642,
          229508,
          237077,
          241497,
          243525,
          244856,
          249508,
          256656,
          361275,
          362355,
          363191,
          364423,
          366521,
          368329,
          373126,
          374860,
          376446,
          377963,
          380908,
          382534,
          383512,
          384636,
          386683,
          388469,
          393190,
          395147,
          396506,
          398109,
          400885,
          402378,
          403353,
          404579,
          406943,
          408525,
          413180,
          415171,
          416476,
          417981
        ]
      },
      "2": {
        "sweep_num": 45,
        "El": -0.0701246109008789,
        "spike_ind": [
          202898,
          204736,
          209482,
          216385,
          221621,
          223757,
          235437,
          238188,
          241455,
          243641,
          249378,
          257234,
          361224,
          362119,
          362959,
          363822,
          364708,
          366928,
          368504,
          373136,
          374824,
          376395,
          378034,
          380834,
          382371,
          383214,
          384517,
          386921,
          388437,
          393117,
          395162,
          396440,
          398042,
          400862,
          401945,
          402947,
          403777,
          404724,
          407869,
          409436,
          413184,
          415217,
          416545,
          418105
        ]
      },
      "5": {
        "sweep_num": null,
        "El": null,
        "spike_ind": null
      },
      "4": {
        "sweep_num": 49,
        "El": -0.0684890213012695,
        "spike_ind": [
          203258,
          218126,
          222685,
          224678,
          237206,
          241856,
          244362,
          249516,
          258118,
          361389,
          362432,
          363273,
          364432,
          366164,
          368264,
          373101,
          374732,
          376428,
          378130,
          380933,
          382544,
          383456,
          384646,
          386891,
          389187,
          393198,
          395193,
          397067,
          398440,
          400932,
          402433,
          403494,
          404671,
          406880,
          408538,
          413251,
          415241,
          416573,
          418126
        ]
      }
    },
    "ramp": {
      "sweep_num": [
        4,
        5,
        6
      ]
    },
    "max_subthresh_long_square": {
      "sweep_num": [
        30
      ]
    },
    "suprathreshold_short_square": {
      "R_testpulsesweep_num": [
        11
      ]
    },
    "subthreshold_short_square": {
      "sweep_num": [
        15
      ]
    }
  },
  "spike_cutting": {
    "NOdeltaV": {
      "slope": 0.3839727870053092,
      "intercept": 0.008822854072073658,
      "cut_length": 68.0,
      "dependencies": null
    }
  },
  "dt_used_for_preprocessor_calculations": 5e-05
}